cookiecutter/.gitignore
cookiecutter/.travis.yml
cookiecutter/Makefile
cookiecutter/README.rst
cookiecutter/cookiecutter.json
cookiecutter/mkpregen.py
cookiecutter/test.sh
cookiecutter/hooks/post_gen_project.py
cookiecutter/hooks/pre_gen_project.py
cookiecutter/hooks/pre_gen_project.py.in
cookiecutter/{{cookiecutter.project_name}}/.editorconfig
cookiecutter/{{cookiecutter.project_name}}/.gitchangelog.rc
cookiecutter/{{cookiecutter.project_name}}/.gitignore
cookiecutter/{{cookiecutter.project_name}}/.hgignore
cookiecutter/{{cookiecutter.project_name}}/.travis.yml
cookiecutter/{{cookiecutter.project_name}}/AUTHORS.rst
cookiecutter/{{cookiecutter.project_name}}/CONTRIBUTING.rst
cookiecutter/{{cookiecutter.project_name}}/HISTORY.rst
cookiecutter/{{cookiecutter.project_name}}/LICENSE
cookiecutter/{{cookiecutter.project_name}}/MANIFEST.in
cookiecutter/{{cookiecutter.project_name}}/Makefile
cookiecutter/{{cookiecutter.project_name}}/README.rst
cookiecutter/{{cookiecutter.project_name}}/git-commit-msg
cookiecutter/{{cookiecutter.project_name}}/pavement.py
cookiecutter/{{cookiecutter.project_name}}/setup.cfg
cookiecutter/{{cookiecutter.project_name}}/setup.py
cookiecutter/{{cookiecutter.project_name}}/tox.ini
cookiecutter/{{cookiecutter.project_name}}/travis_pypi_setup.py
cookiecutter/{{cookiecutter.project_name}}/docs/Makefile
cookiecutter/{{cookiecutter.project_name}}/docs/authors.rst
cookiecutter/{{cookiecutter.project_name}}/docs/conf.py
cookiecutter/{{cookiecutter.project_name}}/docs/contributing.rst
cookiecutter/{{cookiecutter.project_name}}/docs/history.rst
cookiecutter/{{cookiecutter.project_name}}/docs/index.rst
cookiecutter/{{cookiecutter.project_name}}/docs/installation.rst
cookiecutter/{{cookiecutter.project_name}}/docs/make.bat
cookiecutter/{{cookiecutter.project_name}}/docs/readme.rst
cookiecutter/{{cookiecutter.project_name}}/docs/usage.rst
cookiecutter/{{cookiecutter.project_name}}/docs/_static/.keep
nicfit.py-0.8.7.dist-info/LICENSE
nicfit.py-0.8.7.dist-info/METADATA
nicfit.py-0.8.7.dist-info/WHEEL
nicfit.py-0.8.7.dist-info/entry_points.txt
nicfit.py-0.8.7.dist-info/top_level.txt
nicfit.py-0.8.7.dist-info/RECORD
