Metadata-Version: 2.1
Name: nicfit.py
Version: 0.8.7
Summary: Common Python utils (App, logging, config, etc.)
Home-page: https://github.com/nicfit/nicfit.py
Author: Travis Shirk
Author-email: travis@pobox.com
License: MIT
Download-URL: https://github.com/nicfit/nicfit.py/releases/downloads/v0.8.7/nicfit.py-0.8.7.tar.gz
Keywords: python,application,cookiecutter,utils
Platform: Any
Classifier: Intended Audience :: Developers
Classifier: Operating System :: POSIX
Classifier: Natural Language :: English
Classifier: License :: OSI Approved :: MIT License
Classifier: Programming Language :: Python
Classifier: Programming Language :: Python :: 3.6
Classifier: Programming Language :: Python :: 3.7
Classifier: Programming Language :: Python :: 3.8
Classifier: Development Status :: 5 - Production/Stable
Requires-Dist: deprecation
Requires-Dist: attrs
Requires-Dist: PyYaml
Provides-Extra: cookiecutter
Requires-Dist: cookiecutter ; extra == 'cookiecutter'
Provides-Extra: shell
Requires-Dist: prompt-toolkit ; extra == 'shell'
Requires-Dist: pygments ; extra == 'shell'
